{
    "equipment": [
        {
            "index": 1,
            "name": "프라임 엣지",
            "rank": 0,
            "price": 200,
            "script": "공격력 +2",
            "imageIndex": 1,
            "part": 0,
            "attackPower": 2,
            "attackSpeed": 0,
            "attackRange": 0,
            "moveSpeed": 0
        },
        {
            "index": 2,
            "name": "프라임 바디",
            "rank": 0,
            "price": 200,
            "script": "공격력 +1, 공격범위 +1",
            "imageIndex": 2,
            "part": 1,
            "attackPower": 1,
            "attackSpeed": 0,
            "attackRange": 1,
            "moveSpeed": 0
        },
        {
            "index": 3,
            "name": "프라임 핸들",
            "rank": 0,
            "price": 200,
            "script": "공격력 +1, 공격속도 +1",
            "imageIndex": 3,
            "part": 2,
            "attackPower": 1,
            "attackSpeed": 1,
            "attackRange": 0,
            "moveSpeed": 0
        },
        {
            "index": 4,
            "name": "세이버 엣지",
            "rank": 0,
            "price": 200,
            "script": "공격력 -1, 공격속도 +2, 공격범위 +1",
            "imageIndex": 4,
            "part": 0,
            "attackPower": -1,
            "attackSpeed": 2,
            "attackRange": 1,
            "moveSpeed": 0
        },
        {
            "index": 5,
            "name": "세이버 바디",
            "rank": 0,
            "price": 200,
            "script": "공격력 -2, 공격속도 +2, 공격범위 +2",
            "imageIndex": 5,
            "part": 1,
            "attackPower": -2,
            "attackSpeed": 2,
            "attackRange": 2,
            "moveSpeed": 0
        },
        {
            "index": 6,
            "name": "세이버 핸들",
            "rank": 0,
            "price": 200,
            "script": "공격력 -2, 공격속도 +3, 공격범위 +1",
            "imageIndex": 6,
            "part": 2,
            "attackPower": -2,
            "attackSpeed": 3,
            "attackRange": 1,
            "moveSpeed": 0
        },
        {
            "index": 7,
            "name": "타이탄 엣지",
            "rank": 0,
            "price": 200,
            "script": "공격력 +3, 공격속도 -2, 공격범위 +2, 이동속도 -1",
            "imageIndex": 7,
            "part": 0,
            "attackPower": 3,
            "attackSpeed": -2,
            "attackRange": 2,
            "moveSpeed": -1
        },
        {
            "index": 8,
            "name": "타이탄 바디",
            "rank": 0,
            "price": 200,
            "script": "공격력 +2, 공격속도 -2, 공격범위 +3, 이동속도 -1",
            "imageIndex": 8,
            "part": 1,
            "attackPower": 2,
            "attackSpeed": -2,
            "attackRange": 3,
            "moveSpeed": -1
        },
        {
            "index": 9,
            "name": "타이탄 핸들",
            "rank": 0,
            "price": 200,
            "script": "공격력 +2, 공격속도 -1, 공격범위 +2, 이동속도 -1",
            "imageIndex": 9,
            "part": 2,
            "attackPower": 2,
            "attackSpeed": -1,
            "attackRange": 2,
            "moveSpeed": -1
        },
        {
            "index": 10,
            "name": "베론 엣지",
            "rank": 0,
            "price": 200,
            "script": "공격력 +1, 공격속도 +1, 공격범위 -2, 이동속도 +2",
            "imageIndex": 10,
            "part": 0,
            "attackPower": 1,
            "attackSpeed": 1,
            "attackRange": -2,
            "moveSpeed": 2
        },
        {
            "index": 11,
            "name": "베론 바디",
            "rank": 0,
            "price": 200,
            "script": "공격속도 +1, 공격범위 -1, 이동속도 +2",
            "imageIndex": 11,
            "part": 1,
            "attackPower": 0,
            "attackSpeed": 1,
            "attackRange": -1,
            "moveSpeed": 2
        },
        {
            "index": 12,
            "name": "베론 핸들",
            "rank": 0,
            "price": 200,
            "script": "공격속도 +2, 공격범위 -2, 이동속도 +2",
            "imageIndex": 12,
            "part": 2,
            "attackPower": 0,
            "attackSpeed": 2,
            "attackRange": -2,
            "moveSpeed": 2
        },
        {
            "index": 13,
            "name": "프라임 엣지",
            "rank": 1,
            "price": 400,
            "script": "공격력 +4",
            "imageIndex": 13,
            "part": 0,
            "attackPower": 4,
            "attackSpeed": 0,
            "attackRange": 0,
            "moveSpeed": 0
        },
        {
            "index": 14,
            "name": "프라임 바디",
            "rank": 1,
            "price": 400,
            "script": "공격력 +2, 공격범위 +2",
            "imageIndex": 14,
            "part": 1,
            "attackPower": 2,
            "attackSpeed": 0,
            "attackRange": 2,
            "moveSpeed": 0
        },
        {
            "index": 15,
            "name": "프라임 핸들",
            "rank": 1,
            "price": 400,
            "script": "공격력 +2, 공격속도 +2",
            "imageIndex": 15,
            "part": 2,
            "attackPower": 2,
            "attackSpeed": 2,
            "attackRange": 0,
            "moveSpeed": 0
        },
        {
            "index": 16,
            "name": "세이버 엣지",
            "rank": 1,
            "price": 400,
            "script": "공격력 -2, 공격속도 +4, 공격범위 +2",
            "imageIndex": 16,
            "part": 0,
            "attackPower": -2,
            "attackSpeed": 4,
            "attackRange": 2,
            "moveSpeed": 0
        },
        {
            "index": 17,
            "name": "세이버 바디",
            "rank": 1,
            "price": 400,
            "script": "공격력 -4, 공격속도 +4, 공격범위 +4",
            "imageIndex": 17,
            "part": 1,
            "attackPower": -4,
            "attackSpeed": 4,
            "attackRange": 4,
            "moveSpeed": 0
        },
        {
            "index": 18,
            "name": "세이버 핸들",
            "rank": 1,
            "price": 400,
            "script": "공격력 -4, 공격속도 +6, 공격범위 +2",
            "imageIndex": 18,
            "part": 2,
            "attackPower": -4,
            "attackSpeed": 6,
            "attackRange": 2,
            "moveSpeed": 0
        },
        {
            "index": 19,
            "name": "타이탄 엣지",
            "rank": 1,
            "price": 400,
            "script": "공격력 +6, 공격속도 -4, 공격범위 +4, 이동속도 -2",
            "imageIndex": 19,
            "part": 0,
            "attackPower": 6,
            "attackSpeed": -4,
            "attackRange": 4,
            "moveSpeed": -2
        },
        {
            "index": 20,
            "name": "타이탄 바디",
            "rank": 1,
            "price": 400,
            "script": "공격력 +4, 공격속도 -4, 공격범위 +6, 이동속도 -2",
            "imageIndex": 20,
            "part": 1,
            "attackPower": 4,
            "attackSpeed": -4,
            "attackRange": 6,
            "moveSpeed": -2
        },
        {
            "index": 21,
            "name": "타이탄 핸들",
            "rank": 1,
            "price": 400,
            "script": "공격력 +4, 공격속도 -2, 공격범위 +4, 이동속도 -2",
            "imageIndex": 21,
            "part": 2,
            "attackPower": 4,
            "attackSpeed": -2,
            "attackRange": 4,
            "moveSpeed": -2
        },
        {
            "index": 22,
            "name": "베론 엣지",
            "rank": 1,
            "price": 400,
            "script": "공격력 +2, 공격속도 +2, 공격범위 -4, 이동속도 +4",
            "imageIndex": 22,
            "part": 0,
            "attackPower": 2,
            "attackSpeed": 2,
            "attackRange": -4,
            "moveSpeed": 4
        },
        {
            "index": 23,
            "name": "베론 바디",
            "rank": 1,
            "price": 400,
            "script": "공격속도 +2, 공격범위 -2, 이동속도 +4",
            "imageIndex": 23,
            "part": 1,
            "attackPower": 0,
            "attackSpeed": 2,
            "attackRange": -2,
            "moveSpeed": 4
        },
        {
            "index": 24,
            "name": "베론 핸들",
            "rank": 1,
            "price": 400,
            "script": "공격속도 +4, 공격범위 -4, 이동속도 +4",
            "imageIndex": 24,
            "part": 2,
            "attackPower": 0,
            "attackSpeed": 4,
            "attackRange": -4,
            "moveSpeed": 4
        },
        {
            "index": 25,
            "name": "프라임 엣지",
            "rank": 2,
            "price": 750,
            "script": "공격력 +6",
            "imageIndex": 25,
            "part": 0,
            "attackPower": 6,
            "attackSpeed": 0,
            "attackRange": 0,
            "moveSpeed": 0
        },
        {
            "index": 26,
            "name": "프라임 바디",
            "rank": 2,
            "price": 750,
            "script": "공격력 +3, 공격범위 +3",
            "imageIndex": 26,
            "part": 1,
            "attackPower": 3,
            "attackSpeed": 0,
            "attackRange": 3,
            "moveSpeed": 0
        },
        {
            "index": 27,
            "name": "프라임 핸들",
            "rank": 2,
            "price": 750,
            "script": "공격력 +3, 공격속도 +3",
            "imageIndex": 27,
            "part": 2,
            "attackPower": 3,
            "attackSpeed": 3,
            "attackRange": 0,
            "moveSpeed": 0
        },
        {
            "index": 28,
            "name": "세이버 엣지",
            "rank": 2,
            "price": 750,
            "script": "공격력 -3, 공격속도 +6, 공격범위 +3",
            "imageIndex": 28,
            "part": 0,
            "attackPower": -3,
            "attackSpeed": 6,
            "attackRange": 3,
            "moveSpeed": 0
        },
        {
            "index": 29,
            "name": "세이버 바디",
            "rank": 2,
            "price": 750,
            "script": "공격력 -6, 공격속도 +6, 공격범위 +6",
            "imageIndex": 29,
            "part": 1,
            "attackPower": -6,
            "attackSpeed": 6,
            "attackRange": 6,
            "moveSpeed": 0
        },
        {
            "index": 30,
            "name": "세이버 핸들",
            "rank": 2,
            "price": 750,
            "script": "공격력 -6, 공격속도 +9, 공격범위 +3",
            "imageIndex": 30,
            "part": 2,
            "attackPower": -6,
            "attackSpeed": 9,
            "attackRange": 3,
            "moveSpeed": 0
        },
        {
            "index": 31,
            "name": "타이탄 엣지",
            "rank": 2,
            "price": 750,
            "script": "공격력 +9, 공격속도 -6, 공격범위 +6, 이동속도 -3",
            "imageIndex": 31,
            "part": 0,
            "attackPower": 9,
            "attackSpeed": -6,
            "attackRange": 6,
            "moveSpeed": -3
        },
        {
            "index": 32,
            "name": "타이탄 바디",
            "rank": 2,
            "price": 750,
            "script": "공격력 +6, 공격속도 -6, 공격범위 +9, 이동속도 -3",
            "imageIndex": 32,
            "part": 1,
            "attackPower": 6,
            "attackSpeed": -6,
            "attackRange": 9,
            "moveSpeed": -3
        },
        {
            "index": 33,
            "name": "타이탄 핸들",
            "rank": 2,
            "price": 750,
            "script": "공격력 +6, 공격속도 -3, 공격범위 +6, 이동속도 -3",
            "imageIndex": 33,
            "part": 2,
            "attackPower": 6,
            "attackSpeed": -3,
            "attackRange": 6,
            "moveSpeed": -3
        },
        {
            "index": 34,
            "name": "베론 엣지",
            "rank": 2,
            "price": 750,
            "script": "공격력 +3, 공격속도 +3, 공격범위 -6, 이동속도 +6",
            "imageIndex": 34,
            "part": 0,
            "attackPower": 3,
            "attackSpeed": 3,
            "attackRange": -6,
            "moveSpeed": 6
        },
        {
            "index": 35,
            "name": "베론 바디",
            "rank": 2,
            "price": 750,
            "script": "공격속도 +3, 공격범위 -3, 이동속도 +6",
            "imageIndex": 35,
            "part": 1,
            "attackPower": 0,
            "attackSpeed": 3,
            "attackRange": -3,
            "moveSpeed": 6
        },
        {
            "index": 36,
            "name": "베론 핸들",
            "rank": 2,
            "price": 750,
            "script": "공격속도 +6, 공격범위 -6, 이동속도 +6",
            "imageIndex": 36,
            "part": 2,
            "attackPower": 0,
            "attackSpeed": 6,
            "attackRange": -6,
            "moveSpeed": 6
        },
        {
            "index": 37,
            "name": "프라임 엣지",
            "rank": 3,
            "price": 1500,
            "script": "공격력 +8",
            "imageIndex": 37,
            "part": 0,
            "attackPower": 8,
            "attackSpeed": 0,
            "attackRange": 0,
            "moveSpeed": 0
        },
        {
            "index": 38,
            "name": "프라임 바디",
            "rank": 3,
            "price": 1500,
            "script": "공격력 +4, 공격범위 +4",
            "imageIndex": 38,
            "part": 1,
            "attackPower": 4,
            "attackSpeed": 0,
            "attackRange": 4,
            "moveSpeed": 0
        },
        {
            "index": 39,
            "name": "프라임 핸들",
            "rank": 3,
            "price": 1500,
            "script": "공격력 +4, 공격속도 +4",
            "imageIndex": 39,
            "part": 2,
            "attackPower": 4,
            "attackSpeed": 4,
            "attackRange": 0,
            "moveSpeed": 0
        },
        {
            "index": 40,
            "name": "세이버 엣지",
            "rank": 3,
            "price": 1500,
            "script": "공격력 -4, 공격속도 +8, 공격범위 +4",
            "imageIndex": 40,
            "part": 0,
            "attackPower": -4,
            "attackSpeed": 8,
            "attackRange": 4,
            "moveSpeed": 0
        },
        {
            "index": 41,
            "name": "세이버 바디",
            "rank": 3,
            "price": 1500,
            "script": "공격력 -8, 공격속도 +8, 공격범위 +8",
            "imageIndex": 41,
            "part": 1,
            "attackPower": -8,
            "attackSpeed": 8,
            "attackRange": 8,
            "moveSpeed": 0
        },
        {
            "index": 42,
            "name": "세이버 핸들",
            "rank": 3,
            "price": 1500,
            "script": "공격력 -8, 공격속도 +12, 공격범위 +4",
            "imageIndex": 42,
            "part": 2,
            "attackPower": -8,
            "attackSpeed": 12,
            "attackRange": 4,
            "moveSpeed": 0
        },
        {
            "index": 43,
            "name": "타이탄 엣지",
            "rank": 3,
            "price": 1500,
            "script": "공격력 +12, 공격속도 -8, 공격범위 +8, 이동속도 -4",
            "imageIndex": 43,
            "part": 0,
            "attackPower": 12,
            "attackSpeed": -8,
            "attackRange": 8,
            "moveSpeed": -4
        },
        {
            "index": 44,
            "name": "타이탄 바디",
            "rank": 3,
            "price": 1500,
            "script": "공격력 +8, 공격속도 -8, 공격범위 +12, 이동속도 -4",
            "imageIndex": 44,
            "part": 1,
            "attackPower": 8,
            "attackSpeed": -8,
            "attackRange": 12,
            "moveSpeed": -4
        },
        {
            "index": 45,
            "name": "타이탄 핸들",
            "rank": 3,
            "price": 1500,
            "script": "공격력 +8, 공격속도 -4, 공격범위 +8, 이동속도 -4",
            "imageIndex": 45,
            "part": 2,
            "attackPower": 8,
            "attackSpeed": -4,
            "attackRange": 8,
            "moveSpeed": -4
        },
        {
            "index": 46,
            "name": "베론 엣지",
            "rank": 3,
            "price": 1500,
            "script": "공격력 +4, 공격속도 +4, 공격범위 -8, 이동속도 +8",
            "imageIndex": 46,
            "part": 0,
            "attackPower": 4,
            "attackSpeed": 4,
            "attackRange": -8,
            "moveSpeed": 8
        },
        {
            "index": 47,
            "name": "베론 바디",
            "rank": 3,
            "price": 1500,
            "script": "공격속도 +4, 공격범위 -4, 이동속도 +8",
            "imageIndex": 47,
            "part": 1,
            "attackPower": 0,
            "attackSpeed": 4,
            "attackRange": -4,
            "moveSpeed": 8
        },
        {
            "index": 48,
            "name": "베론 핸들",
            "rank": 3,
            "price": 1500,
            "script": "공격속도 +8, 공격범위 -8, 이동속도 +8",
            "imageIndex": 48,
            "part": 2,
            "attackPower": 0,
            "attackSpeed": 8,
            "attackRange": -8,
            "moveSpeed": 8
        }
    ]
}