{
    "difficulty": [
        {
            "recommandLv": 1,
            "rewardExp": "1",
            "goalMoney": 750,
            "enemyStatus": 1.0,
            "enemyRespawn": 1.0,
            "normalEnhance": 0.0,
            "eliteEnhance": 0.0,
            "dropRank": 1,
            "recommandCP": 1.0
        },
        {
            "recommandLv": 3,
            "rewardExp": "3",
            "goalMoney": 1500,
            "enemyStatus": 1.1,
            "enemyRespawn": 1.1,
            "normalEnhance": 0.0,
            "eliteEnhance": 0.0,
            "dropRank": 2,
            "recommandCP": 1.2
        },
        {
            "recommandLv": 6,
            "rewardExp": "8",
            "goalMoney": 2750,
            "enemyStatus": 1.3,
            "enemyRespawn": 1.3,
            "normalEnhance": 0.0,
            "eliteEnhance": 0.04,
            "dropRank": 4,
            "recommandCP": 1.5
        },
        {
            "recommandLv": 9,
            "rewardExp": "20",
            "goalMoney": 5000,
            "enemyStatus": 1.6,
            "enemyRespawn": 1.6,
            "normalEnhance": 0.0,
            "eliteEnhance": 0.08,
            "dropRank": 6,
            "recommandCP": 1.9
        },
        {
            "recommandLv": 12,
            "rewardExp": "48",
            "goalMoney": 8500,
            "enemyStatus": 2.1,
            "enemyRespawn": 2.1,
            "normalEnhance": 0.05,
            "eliteEnhance": 0.15,
            "dropRank": 9,
            "recommandCP": 2.5
        },
        {
            "recommandLv": 15,
            "rewardExp": "105",
            "goalMoney": 13500,
            "enemyStatus": 2.8,
            "enemyRespawn": 2.8,
            "normalEnhance": 0.1,
            "eliteEnhance": 0.25,
            "dropRank": 12,
            "recommandCP": 3.4
        },
        {
            "recommandLv": 18,
            "rewardExp": "210",
            "goalMoney": 20000,
            "enemyStatus": 3.8,
            "enemyRespawn": 3.8,
            "normalEnhance": 0.2,
            "eliteEnhance": 0.4,
            "dropRank": 15,
            "recommandCP": 4.7
        },
        {
            "recommandLv": 20,
            "rewardExp": "진엔딩",
            "goalMoney": 30000,
            "enemyStatus": 5.0,
            "enemyRespawn": 5.0,
            "normalEnhance": 0.3,
            "eliteEnhance": 0.55,
            "dropRank": 18,
            "recommandCP": 6.2
        }
    ]
}

